<?xml version="1.0" encoding="UTF-8"?><record_update table="sys_metadata_link">
    <sys_metadata_link action="INSERT_OR_UPDATE">
        <directory>unload.demo</directory>
        <documentkey>cacdf9b34f302200e0cbd49f0310c7c2</documentkey>
        <payload><![CDATA[<?xml version="1.0" encoding="UTF-8"?><record_update>
    <sys_choice action="INSERT_OR_UPDATE" field="run_type" table="scheduled_data_export" version="3">
        <sys_choice action="INSERT_OR_UPDATE">
            <dependent_value/>
            <element>run_type</element>
            <hint/>
            <inactive>false</inactive>
            <label>Daily</label>
            <language>en</language>
            <name>scheduled_data_export</name>
            <sequence>0</sequence>
            <sys_created_by>system</sys_created_by>
            <sys_created_on>2016-07-30 17:25:24</sys_created_on>
            <sys_domain>global</sys_domain>
            <sys_domain_path>/</sys_domain_path>
            <sys_id>86cdf9b34f302200e0cbd49f0310c7c2</sys_id>
            <sys_mod_count>0</sys_mod_count>
            <sys_updated_by>system</sys_updated_by>
            <sys_updated_on>2016-07-30 17:25:24</sys_updated_on>
            <value>daily</value>
        </sys_choice>
        <sys_choice action="INSERT_OR_UPDATE">
            <dependent_value/>
            <element>run_type</element>
            <hint/>
            <inactive>false</inactive>
            <label>Weekly</label>
            <language>en</language>
            <name>scheduled_data_export</name>
            <sequence>1</sequence>
            <sys_created_by>system</sys_created_by>
            <sys_created_on>2016-07-30 17:25:24</sys_created_on>
            <sys_domain>global</sys_domain>
            <sys_domain_path>/</sys_domain_path>
            <sys_id>c6cdf9b34f302200e0cbd49f0310c7c2</sys_id>
            <sys_mod_count>0</sys_mod_count>
            <sys_updated_by>system</sys_updated_by>
            <sys_updated_on>2016-07-30 17:25:24</sys_updated_on>
            <value>weekly</value>
        </sys_choice>
        <sys_choice action="INSERT_OR_UPDATE">
            <dependent_value/>
            <element>run_type</element>
            <hint/>
            <inactive>false</inactive>
            <label>Monthly</label>
            <language>en</language>
            <name>scheduled_data_export</name>
            <sequence>2</sequence>
            <sys_created_by>system</sys_created_by>
            <sys_created_on>2016-07-30 17:25:24</sys_created_on>
            <sys_domain>global</sys_domain>
            <sys_domain_path>/</sys_domain_path>
            <sys_id>0acdf9b34f302200e0cbd49f0310c7c2</sys_id>
            <sys_mod_count>0</sys_mod_count>
            <sys_updated_by>system</sys_updated_by>
            <sys_updated_on>2016-07-30 17:25:24</sys_updated_on>
            <value>monthly</value>
        </sys_choice>
        <sys_choice action="INSERT_OR_UPDATE">
            <dependent_value/>
            <element>run_type</element>
            <hint/>
            <inactive>false</inactive>
            <label>Periodically</label>
            <language>en</language>
            <name>scheduled_data_export</name>
            <sequence>3</sequence>
            <sys_created_by>system</sys_created_by>
            <sys_created_on>2016-07-30 17:25:24</sys_created_on>
            <sys_domain>global</sys_domain>
            <sys_domain_path>/</sys_domain_path>
            <sys_id>4acdf9b34f302200e0cbd49f0310c7c2</sys_id>
            <sys_mod_count>0</sys_mod_count>
            <sys_updated_by>system</sys_updated_by>
            <sys_updated_on>2016-07-30 17:25:24</sys_updated_on>
            <value>periodically</value>
        </sys_choice>
        <sys_choice action="INSERT_OR_UPDATE">
            <dependent_value/>
            <element>run_type</element>
            <hint/>
            <inactive>false</inactive>
            <label>After Parent Runs</label>
            <language>en</language>
            <name>scheduled_data_export</name>
            <sequence>99</sequence>
            <sys_created_by>system</sys_created_by>
            <sys_created_on>2016-07-30 17:25:24</sys_created_on>
            <sys_domain>global</sys_domain>
            <sys_domain_path>/</sys_domain_path>
            <sys_id>8acdf9b34f302200e0cbd49f0310c7c2</sys_id>
            <sys_mod_count>0</sys_mod_count>
            <sys_updated_by>system</sys_updated_by>
            <sys_updated_on>2016-07-30 17:25:24</sys_updated_on>
            <value>parent</value>
        </sys_choice>
        <sys_choice_set action="INSERT_OR_UPDATE">
            <element>run_type</element>
            <name>scheduled_data_export</name>
            <sys_class_name>sys_choice_set</sys_class_name>
            <sys_created_by>system</sys_created_by>
            <sys_created_on>2016-07-30 17:25:24</sys_created_on>
            <sys_customer_update>false</sys_customer_update>
            <sys_id>cacdf9b34f302200e0cbd49f0310c7c2</sys_id>
            <sys_mod_count>0</sys_mod_count>
            <sys_name>run_type</sys_name>
            <sys_package display_value="Basic Export Set Functionality" source="com.glide.system_export_set">95cdf9b34f302200e0cbd49f0310c784</sys_package>
            <sys_policy/>
            <sys_replace_on_upgrade>false</sys_replace_on_upgrade>
            <sys_scope display_value="Global">global</sys_scope>
            <sys_update_name>sys_choice_scheduled_data_export_run_type</sys_update_name>
            <sys_updated_by>system</sys_updated_by>
            <sys_updated_on>2016-07-30 17:25:24</sys_updated_on>
        </sys_choice_set>
    </sys_choice>
</record_update>
]]></payload>
        <sys_class_name>sys_metadata_link</sys_class_name>
        <sys_created_by>Anthony.Sheculski-ad</sys_created_by>
        <sys_created_on>2020-01-20 06:02:20</sys_created_on>
        <sys_customer_update>false</sys_customer_update>
        <sys_id>8dfa26401be6489066d6c91e1e4bcb12</sys_id>
        <sys_mod_count>0</sys_mod_count>
        <sys_name>run_type</sys_name>
        <sys_package display_value="SOE Retrofit Support" source="x_clear_soe_retro">8a2718d41bf840d066d6c91e1e4bcbbf</sys_package>
        <sys_policy/>
        <sys_replace_on_upgrade>false</sys_replace_on_upgrade>
        <sys_scope display_value="SOE Retrofit Support">8a2718d41bf840d066d6c91e1e4bcbbf</sys_scope>
        <sys_update_name>sys_metadata_link_8dfa26401be6489066d6c91e1e4bcb12</sys_update_name>
        <sys_updated_by>Anthony.Sheculski-ad</sys_updated_by>
        <sys_updated_on>2020-01-20 06:02:20</sys_updated_on>
        <tablename>sys_metadata</tablename>
    </sys_metadata_link>
</record_update>
