<?xml version="1.0" encoding="UTF-8"?><record_update table="sys_metadata_link">
    <sys_metadata_link action="INSERT_OR_UPDATE">
        <directory>unload.demo</directory>
        <documentkey>a5ed11314f0331007c0cacb14210c7a9</documentkey>
        <payload><![CDATA[<?xml version="1.0" encoding="UTF-8"?><record_update>
    <sys_choice action="INSERT_OR_UPDATE" field="explain_status" table="sys_querystat" version="3">
        <sys_choice action="INSERT_OR_UPDATE">
            <dependent_value/>
            <element>explain_status</element>
            <hint/>
            <inactive>false</inactive>
            <label>Cannot Explain</label>
            <language>en</language>
            <name>sys_querystat</name>
            <sequence/>
            <sys_created_by>system</sys_created_by>
            <sys_created_on>2015-03-27 17:46:04</sys_created_on>
            <sys_domain>global</sys_domain>
            <sys_domain_path>/</sys_domain_path>
            <sys_id>25ed11314f0331007c0cacb14210c7a9</sys_id>
            <sys_mod_count>0</sys_mod_count>
            <sys_updated_by>system</sys_updated_by>
            <sys_updated_on>2015-03-27 17:46:04</sys_updated_on>
            <value>cannot</value>
        </sys_choice>
        <sys_choice action="INSERT_OR_UPDATE">
            <dependent_value/>
            <element>explain_status</element>
            <hint/>
            <inactive>false</inactive>
            <label>Error During Explain</label>
            <language>en</language>
            <name>sys_querystat</name>
            <sequence/>
            <sys_created_by>system</sys_created_by>
            <sys_created_on>2015-03-27 17:46:04</sys_created_on>
            <sys_domain>global</sys_domain>
            <sys_domain_path>/</sys_domain_path>
            <sys_id>65ed11314f0331007c0cacb14210c7a9</sys_id>
            <sys_mod_count>0</sys_mod_count>
            <sys_updated_by>system</sys_updated_by>
            <sys_updated_on>2015-03-27 17:46:04</sys_updated_on>
            <value>error</value>
        </sys_choice>
        <sys_choice action="INSERT_OR_UPDATE">
            <dependent_value/>
            <element>explain_status</element>
            <hint/>
            <inactive>false</inactive>
            <label>Explained</label>
            <language>en</language>
            <name>sys_querystat</name>
            <sequence/>
            <sys_created_by>system</sys_created_by>
            <sys_created_on>2015-03-27 17:46:04</sys_created_on>
            <sys_domain>global</sys_domain>
            <sys_domain_path>/</sys_domain_path>
            <sys_id>e1ed11314f0331007c0cacb14210c7a9</sys_id>
            <sys_mod_count>0</sys_mod_count>
            <sys_updated_by>system</sys_updated_by>
            <sys_updated_on>2015-03-27 17:46:04</sys_updated_on>
            <value>explained</value>
        </sys_choice>
        <sys_choice action="INSERT_OR_UPDATE">
            <dependent_value/>
            <element>explain_status</element>
            <hint/>
            <inactive>false</inactive>
            <label>Ready</label>
            <language>en</language>
            <name>sys_querystat</name>
            <sequence/>
            <sys_created_by>system</sys_created_by>
            <sys_created_on>2015-03-27 17:46:04</sys_created_on>
            <sys_domain>global</sys_domain>
            <sys_domain_path>/</sys_domain_path>
            <sys_id>a1ed11314f0331007c0cacb14210c7a9</sys_id>
            <sys_mod_count>0</sys_mod_count>
            <sys_updated_by>system</sys_updated_by>
            <sys_updated_on>2015-03-27 17:46:04</sys_updated_on>
            <value>ready</value>
        </sys_choice>
        <sys_choice_set action="INSERT_OR_UPDATE">
            <element>explain_status</element>
            <name>sys_querystat</name>
            <sys_class_name>sys_choice_set</sys_class_name>
            <sys_created_by>system</sys_created_by>
            <sys_created_on>2015-03-27 17:46:04</sys_created_on>
            <sys_customer_update>false</sys_customer_update>
            <sys_id>a5ed11314f0331007c0cacb14210c7a9</sys_id>
            <sys_mod_count>0</sys_mod_count>
            <sys_name>explain_status</sys_name>
            <sys_package display_value="System (apps/system1)" source="apps/system1">8ded11314f0331007c0cacb14210c767</sys_package>
            <sys_policy/>
            <sys_replace_on_upgrade>false</sys_replace_on_upgrade>
            <sys_scope display_value="Global">global</sys_scope>
            <sys_update_name>sys_choice_sys_querystat_explain_status</sys_update_name>
            <sys_updated_by>system</sys_updated_by>
            <sys_updated_on>2015-03-27 17:46:04</sys_updated_on>
        </sys_choice_set>
    </sys_choice>
</record_update>
]]></payload>
        <sys_class_name>sys_metadata_link</sys_class_name>
        <sys_created_by>Anthony.Sheculski-ad</sys_created_by>
        <sys_created_on>2020-01-20 06:03:29</sys_created_on>
        <sys_customer_update>false</sys_customer_update>
        <sys_id>823b66801be6489066d6c91e1e4bcb1b</sys_id>
        <sys_mod_count>0</sys_mod_count>
        <sys_name>explain_status</sys_name>
        <sys_package display_value="SOE Retrofit Support" source="x_clear_soe_retro">8a2718d41bf840d066d6c91e1e4bcbbf</sys_package>
        <sys_policy/>
        <sys_replace_on_upgrade>false</sys_replace_on_upgrade>
        <sys_scope display_value="SOE Retrofit Support">8a2718d41bf840d066d6c91e1e4bcbbf</sys_scope>
        <sys_update_name>sys_metadata_link_823b66801be6489066d6c91e1e4bcb1b</sys_update_name>
        <sys_updated_by>Anthony.Sheculski-ad</sys_updated_by>
        <sys_updated_on>2020-01-20 06:03:29</sys_updated_on>
        <tablename>sys_metadata</tablename>
    </sys_metadata_link>
</record_update>
